LICENSE
README.md
pyproject.toml
setup.py
DeepCell.egg-info/PKG-INFO
DeepCell.egg-info/SOURCES.txt
DeepCell.egg-info/dependency_links.txt
DeepCell.egg-info/requires.txt
DeepCell.egg-info/top_level.txt
deepcell/__init__.py
deepcell/_version.py
deepcell/callbacks.py
deepcell/callbacks_test.py
deepcell/losses.py
deepcell/losses_test.py
deepcell/metrics.py
deepcell/running.py
deepcell/running_test.py
deepcell/tracking.py
deepcell/training.py
deepcell/applications/__init__.py
deepcell/applications/application.py
deepcell/applications/application_test.py
deepcell/applications/cell_tracking.py
deepcell/applications/cell_tracking_test.py
deepcell/applications/cytoplasm_segmentation.py
deepcell/applications/cytoplasm_segmentation_test.py
deepcell/applications/label_detection.py
deepcell/applications/label_detection_test.py
deepcell/applications/mesmer.py
deepcell/applications/mesmer_test.py
deepcell/applications/multiplex_segmentation.py
deepcell/applications/nuclear_segmentation.py
deepcell/applications/nuclear_segmentation_test.py
deepcell/applications/scale_detection.py
deepcell/applications/scale_detection_test.py
deepcell/data/__init__.py
deepcell/data/tracking.py
deepcell/data/tracking_test.py
deepcell/datasets/__init__.py
deepcell/datasets/dataset.py
deepcell/datasets/dataset_test.py
deepcell/datasets/dynamic_nuclear_net.py
deepcell/datasets/spot_net.py
deepcell/datasets/tissue_net.py
deepcell/image_generators/__init__.py
deepcell/image_generators/cropping.py
deepcell/image_generators/fully_convolutional.py
deepcell/image_generators/image_generators_test.py
deepcell/image_generators/sample.py
deepcell/image_generators/scale.py
deepcell/image_generators/semantic.py
deepcell/image_generators/tracking.py
deepcell/layers/__init__.py
deepcell/layers/location.py
deepcell/layers/location_test.py
deepcell/layers/normalization.py
deepcell/layers/normalization_test.py
deepcell/layers/padding.py
deepcell/layers/padding_test.py
deepcell/layers/pooling.py
deepcell/layers/pooling_test.py
deepcell/layers/temporal.py
deepcell/layers/temporal_test.py
deepcell/layers/tensor_product.py
deepcell/layers/tensor_product_test.py
